hobrus_rabbitmq/__init__.py
hobrus_rabbitmq/broker.py
hobrus_rabbitmq/publisher.py
hobrus_rabbitmq/subscriber.py
hobrus_rabbitmq-0.1.0.dist-info/METADATA
hobrus_rabbitmq-0.1.0.dist-info/WHEEL
hobrus_rabbitmq-0.1.0.dist-info/top_level.txt
hobrus_rabbitmq-0.1.0.dist-info/RECORD
