Metadata-Version: 2.1
Name: hobrus-rabbitmq
Version: 0.1.0
Summary: Simple RabbitMQ wrapper using FastStream for easy message publishing and subscribing in Python
Home-page: https://github.com/Hobrus/SimpleRabbitMQFastStreamByHobrus
Author: Suhobrus Boris
Author-email: bhobrus@gmail.com
Project-URL: Bug Reports, https://github.com/Hobrus/SimpleRabbitMQFastStreamByHobrus/issues
Project-URL: Source, https://github.com/Hobrus/SimpleRabbitMQFastStreamByHobrus
Keywords: rabbitmq,faststream,messaging,queue
Classifier: Development Status :: 3 - Alpha
Classifier: Intended Audience :: Developers
Classifier: License :: OSI Approved :: MIT License
Classifier: Programming Language :: Python :: 3
Classifier: Programming Language :: Python :: 3.7
Classifier: Programming Language :: Python :: 3.8
Classifier: Programming Language :: Python :: 3.9
Classifier: Programming Language :: Python :: 3.10
Classifier: Programming Language :: Python :: 3.11
Requires-Python: >=3.7
Requires-Dist: faststream[rabbit]
